Metadata-Version: 2.1
Name: pdrle
Version: 0.5.0
Summary: python package for run length encoding on pandas Series
Home-page: https://github.com/darshanbaral/pdrle
Author: Darshan Baral
Author-email: darshanbaral@gmail.com
License: MIT
Download-URL: https://github.com/darshanbaral/pdrle/archive/refs/tags/0.5.0.tar.gz
Platform: UNKNOWN
License-File: LICENSE
